MANIFEST.in
README.rst
history.rst
setup.py
version.txt
cherrypy_cgiserver.egg-info/PKG-INFO
cherrypy_cgiserver.egg-info/SOURCES.txt
cherrypy_cgiserver.egg-info/dependency_links.txt
cherrypy_cgiserver.egg-info/top_level.txt
cpcgiserver/__init__.py
cpcgiserver/lib/__init__.py
cpcgiserver/lib/format_.py
examples/php_server_simple/php_server_simple.py
examples/php_server_simple/php_server_simple_subdir.py
examples/php_server_simple/phpinfo.php
examples/php_server_simple/simple_page.php
examples/php_server_simple/simple_page_with_sleep.php
examples/php_server_simple/testsubdir/index.html
examples/php_server_simple/testsubdir/phpinfo.php
examples/php_server_simple/testsubdir/simple_page.php
examples/php_server_with_staticfiles/php_server_with_staticfiles.py
examples/php_server_with_staticfiles/phpinfo.php
examples/php_server_with_staticfiles/simple_page.php
examples/php_server_with_staticfiles/images/cherrypy.png
examples/php_server_with_staticfiles/testsubdir/index.html
examples/php_server_with_staticfiles/testsubdir/phpinfo.php
examples/php_server_with_staticfiles/testsubdir/simple_page.php
examples/python_server_simple/python_server_simple.py
examples/python_server_simple/pycgi/simple_page.py
examples/python_server_simple/pycgi/simple_page_with_sleep.py