Metadata-Version: 1.1
Name: cherrypy-cgiserver
Version: 0.3.5
Summary: Python CGI Server - Perfect To Deliver PHP Files Within A Python CherryPy Application
Home-page: http://gerold-penz.github.com/cherrypy-cgiserver/
Author: Gerold Penz
Author-email: gerold@halvar.at
License: UNKNOWN
Download-URL: https://github.com/gerold-penz/cherrypy-cgiserver/raw/master/dist/cherrypy-cgiserver-0.3.5.tar.gz
Keywords: CherryPy Web CGI Tool
Platform: UNKNOWN
Classifier: Development Status :: 5 - Production/Stable
Classifier: Environment :: Web Environment
Classifier: Framework :: CherryPy
Classifier: Intended Audience :: Developers
Classifier: Intended Audience :: System Administrators
Classifier: License :: OSI Approved :: GNU Library or Lesser General Public License (LGPL)
Classifier: License :: OSI Approved :: MIT License
Classifier: Operating System :: OS Independent
Classifier: Programming Language :: Python :: 2
Classifier: Topic :: Internet :: WWW/HTTP :: Dynamic Content :: CGI Tools/Libraries
Classifier: Topic :: Internet :: WWW/HTTP :: HTTP Servers
Classifier: Topic :: Internet :: WWW/HTTP :: WSGI :: Application
Classifier: Topic :: Internet :: WWW/HTTP :: WSGI :: Middleware
Classifier: Topic :: Internet :: WWW/HTTP :: WSGI :: Server
